main.py
xserver_cli-0.1.2.dist-info/licenses/LICENSE
xserver_cli-0.1.2.dist-info/METADATA
xserver_cli-0.1.2.dist-info/WHEEL
xserver_cli-0.1.2.dist-info/entry_points.txt
xserver_cli-0.1.2.dist-info/top_level.txt
xserver_cli-0.1.2.dist-info/RECORD
