Metadata-Version: 2.4
Name: xserver-cli
Version: 0.1.2
Summary: A command line tool for XServer
Project-URL: Repository, https://github.com/GitHub30/xserver-cli
Requires-Python: >=3.7
License-File: LICENSE
Requires-Dist: requests-html
Requires-Dist: typer
Requires-Dist: pickledb
Dynamic: license-file
